{
  "_meta": {
    "item_class": {
      "en": "Armour",
      "ch": "防具"
    },
    "localization": {
      "en": "Campaign AR/EV",
      "ch": "过渡防具 AR/EV"
    },
    "theme_category": "Campaign"
  },
  "mapping": {
    "Scale Vest": "Camp AR-EV Early",
    "Fishscale Gauntlets": "Camp AR-EV Early",
    "Battered Helm": "Camp AR-EV Early",
    "Rotted Round Shield": "Camp AR-EV Early",
    "Leatherscale Boots": "Camp AR-EV Early",
    "Light Brigandine": "Camp AR-EV Early",
    "Fir Round Shield": "Camp AR-EV Early",
    "Sallet": "Camp AR-EV Early",
    "Ironscale Gauntlets": "Camp AR-EV Early",
    "Scale Doublet": "Camp AR-EV Early",
    "Ironscale Boots": "Camp AR-EV Early",
    "Studded Round Shield": "Camp AR-EV Early",
    "Infantry Brigandine": "Camp AR-EV Early",
    "Visored Sallet": "Camp AR-EV Early",
    "Bronzescale Gauntlets": "Camp AR-EV Early",
    "Scarlet Round Shield": "Camp AR-EV Early",
    "Full Scale Armour": "Camp AR-EV Early",
    "Bronzescale Boots": "Camp AR-EV Early",
    "Soldier's Brigandine": "Camp AR-EV Early",
    "Gilded Sallet": "Camp AR-EV Early",
    "Splendid Round Shield": "Camp AR-EV Early",
    "Field Lamellar": "Camp AR-EV Mid",
    "Steelscale Boots": "Camp AR-EV Mid",
    "Steelscale Gauntlets": "Camp AR-EV Mid",
    "Secutor Helm": "Camp AR-EV Mid",
    "Wyrmscale Doublet": "Camp AR-EV Mid",
    "Maple Round Shield": "Camp AR-EV Mid",
    "Hussar Brigandine": "Camp AR-EV Mid",
    "Serpentscale Boots": "Camp AR-EV Mid",
    "Serpentscale Gauntlets": "Camp AR-EV Mid",
    "Fencer Helm": "Camp AR-EV Mid",
    "Spiked Round Shield": "Camp AR-EV Mid",
    "Full Wyrmscale": "Camp AR-EV Late",
    "Wyrmscale Gauntlets": "Camp AR-EV Late",
    "Crimson Round Shield": "Camp AR-EV Late",
    "Commander's Brigandine": "Camp AR-EV Late",
    "Wyrmscale Boots": "Camp AR-EV Late",
    "Lacquered Helmet": "Camp AR-EV Late",
    "Battle Lamellar": "Camp AR-EV Late",
    "Baroque Round Shield": "Camp AR-EV Late",
    "Dragonscale Doublet": "Camp AR-EV PreEndgame",
    "Fluted Bascinet": "Camp AR-EV PreEndgame",
    "Teak Round Shield": "Camp AR-EV PreEndgame",
    "Hydrascale Boots": "Camp AR-EV PreEndgame",
    "Hydrascale Gauntlets": "Camp AR-EV PreEndgame",
    "Desert Brigandine": "Camp AR-EV PreEndgame",
    "Spiny Round Shield": "Camp AR-EV PreEndgame",
    "Full Dragonscale": "Camp AR-EV PreEndgame",
    "Pig-Faced Bascinet": "Camp AR-EV PreEndgame",
    "Dragonscale Boots": "Camp AR-EV PreEndgame",
    "General's Brigandine": "Camp AR-EV PreEndgame",
    "Cardinal Round Shield": "Camp AR-EV PreEndgame",
    "Dragonscale Gauntlets": "Camp AR-EV PreEndgame",
    "Nightmare Bascinet": "Camp AR-EV PreEndgame"
  }
}
