{
  "Sceptres": {
    "_meta": {
      "theme_category": "Sceptres",
      "localization": {
        "en": "Sceptres",
        "ch": "短杖"
      }
    },
    "Tier 0 Sceptres": {
      "hideable": false,
      "theme": {
        "Tier": 0
      },
      "sound": {
        "default_sound_id": 6,
        "sharket_sound_id": "顶级底材.mp3"
      },
      "localization": {
        "en": "T0: i83+ Top Sceptres",
        "ch": "T0: 顶级短杖(83+)"
      },
      "show_in_editor": false
    },
    "Tier 1 Sceptres": {
      "hideable": false,
      "theme": {
        "Tier": 1
      },
      "sound": {
        "default_sound_id": 1,
        "sharket_sound_id": "精品装备.mp3"
      },
      "localization": {
        "en": "T1: High End",
        "ch": "T1: 优质短杖"
      }
    },
    "Tier Hide Sceptres": {
      "hideable": true,
      "is_hide_tier": true,
      "theme": {
        "Tier": 9
      },
      "sound": {
        "default_sound_id": -1,
        "sharket_sound_id": null
      },
      "localization": {
        "en": "Hide",
        "ch": "隐藏"
      }
    }
  }
}