{
  "Tinctures": {
    "_meta": {
      "theme_category": "Campaign",
      "localization": {
        "en": "Tinctures",
        "ch": "酊剂"
      },
      "tier_order": [
        "Lv tincture any Tinctures"
      ]
    },
    "Lv tincture any Tinctures": {
      "_lv": true,
      "class_condition": true,
      "conditions": {
        "ItemLevel": "<= 67",
        "Class": "== \"Tinctures\"",
        "AreaLevel": "<= 67"
      },
      "hideable": true,
      "theme": {
        "Tier": 4
      },
      "sound": {
        "default_sound_id": -1,
        "sharket_sound_id": null
      },
      "lv_group": {
        "axis": "always",
        "key": "Tinctures"
      },
      "localization": {
        "en": "Leveling: tincture any (Tinctures)",
        "ch": "过渡: 酊剂 any"
      },
      "_source": {
        "path": "leveling->tincture",
        "tier": "any",
        "order": 4
      }
    }
  }
}
